fentoboardimage/Arrows.py
fentoboardimage/Checkerboard.py
fentoboardimage/Coordinates.py
fentoboardimage/FenParser.py
fentoboardimage/Pieces.py
fentoboardimage/Utils.py
fentoboardimage/__init__.py
fentoboardimage/fen_parser.py
fentoboardimage/main.py
fentoboardimage-1.4.1.dist-info/METADATA
fentoboardimage-1.4.1.dist-info/WHEEL
fentoboardimage-1.4.1.dist-info/licenses/LICENSE
fentoboardimage-1.4.1.dist-info/RECORD
