Metadata-Version: 2.4
Name: fentoboardimage
Version: 1.4.1
Summary: FenToBoardImage takes a Fen string representing a Chess position, and renders a Pillow image of the resulting position.
Author-email: Reed Krawiec <reedkrawiec@gmail.com>
License-Expression: GPL-3.0
License-File: LICENSE
Requires-Python: >=3.8
Requires-Dist: pillow>=9.0.0
